{
  "appKey": "",
  "appSecret": "",
  "excludeScenes": [],
  "includeAnySDK": false,
  "includeSDKBox": false,
  "inlineSpriteFrames": true,
  "inlineSpriteFrames_native": false,
  "jailbreakPlatform": false,
  "md5Cache": false,
  "mergeStartScene": false,
  "oauthLoginServer": "",
  "optimizeHotUpdate": false,
  "orientation": {
    "landscapeLeft": true,
    "landscapeRight": true,
    "portrait": false,
    "upsideDown": false
  },
  "packageName": "com.dinosaur.dice",
  "privateKey": "",
  "startScene": "b81fd48c-8a39-4a1c-903b-04f73e013aec",
  "title": "dice",
  "webOrientation": "landscape",
  "renderMode": "0"
}